kirux189894.py
kirux189894-0.1.dist-info/METADATA
kirux189894-0.1.dist-info/WHEEL
kirux189894-0.1.dist-info/entry_points.txt
kirux189894-0.1.dist-info/top_level.txt
kirux189894-0.1.dist-info/RECORD
